pytest_firefox/__init__.py
pytest_firefox/pytest_firefox.py
pytest_firefox-0.2.0.dist-info/LICENSE
pytest_firefox-0.2.0.dist-info/METADATA
pytest_firefox-0.2.0.dist-info/WHEEL
pytest_firefox-0.2.0.dist-info/entry_points.txt
pytest_firefox-0.2.0.dist-info/RECORD
