Metadata-Version: 2.1
Name: pytest-firefox
Version: 0.2.0
Summary: 
License: MIT
Author: Benjamin Forehand Jr
Author-email: bforehand@mozilla.com
Requires-Python: >=3.12,<3.14
Classifier: License :: OSI Approved :: MIT License
Classifier: Programming Language :: Python :: 3
Classifier: Programming Language :: Python :: 3.12
Classifier: Programming Language :: Python :: 3.13
